pycconverter/__init__.py
pycconverter/pyc_converter.py
pycconverter-0.0.6.dist-info/WHEEL
pycconverter-0.0.6.dist-info/METADATA
pycconverter-0.0.6.dist-info/RECORD
