Metadata-Version: 2.1
Name: pycconverter
Version: 0.0.6
Summary: convert all python script to pyc file in given directory
Home-page: https://github.com/MonadWizard/pycconverter
License: MIT
Author: MonadWizard
Author-email: monad.wizard.r@gmail.com
Requires-Python: >=3.6,<4.0
Classifier: License :: OSI Approved :: MIT License
Classifier: Operating System :: OS Independent
Classifier: Programming Language :: Python :: 3
Classifier: Programming Language :: Python :: 3.10
Classifier: Programming Language :: Python :: 3.6
Classifier: Programming Language :: Python :: 3.7
Classifier: Programming Language :: Python :: 3.8
Classifier: Programming Language :: Python :: 3.9
Project-URL: Repository, https://github.com/MonadWizard/pycconverter
